src/__init__.py
src/login.py
src/main.py
src/utils.py
bjut_internet_login_tool-0.1.15.dist-info/METADATA
bjut_internet_login_tool-0.1.15.dist-info/WHEEL
bjut_internet_login_tool-0.1.15.dist-info/entry_points.txt
bjut_internet_login_tool-0.1.15.dist-info/top_level.txt
bjut_internet_login_tool-0.1.15.dist-info/RECORD
