Metadata-Version: 2.1
Name: bjut-internet-login-tool
Version: 0.1.15
Summary: BJUT Internet Login Tool for command line
Home-page: https://github.com/Ilcyb/BJUTInternetLogin
Author: ilcyb
Author-email: hybmail1996@gmail.com
License: UNKNOWN
Platform: UNKNOWN
Classifier: Programming Language :: Python :: 3
Classifier: License :: OSI Approved :: MIT License
Classifier: Operating System :: OS Independent
Requires-Dist: requests
Requires-Dist: bs4
Requires-Dist: packaging
